texiv/__init__.py
texiv/utils.py
texiv/cli/__init__.py
texiv/config/__init__.py
texiv/config/example.config.toml
texiv/core/__init__.py
texiv/core/texiv.py
texiv/core/utils.py
texiv/core/chunk/__init__.py
texiv/core/chunk/stopwords/README.md
texiv/core/chunk/stopwords/baidu_stopwords.txt
texiv/core/chunk/stopwords/cn_stopwords.txt
texiv/core/chunk/stopwords/hit_stopwords.txt
texiv/core/chunk/stopwords/scu_stopwords.txt
texiv/core/embed/__init__.py
texiv/core/filter/__init__.py
texiv/core/similarity/__init__.py
texiv/stata/__init__.py
texiv-0.1.10.dist-info/METADATA
texiv-0.1.10.dist-info/WHEEL
texiv-0.1.10.dist-info/entry_points.txt
texiv-0.1.10.dist-info/licenses/LICENSE
texiv-0.1.10.dist-info/RECORD
