Metadata-Version: 2.4
Name: TexIV
Version: 0.1.10
Summary: A machine learning–based method for transforming text into instrumental variables (IV).
Project-URL: Homepage, https://github.com/sepinetam/texiv
License-File: LICENSE
Requires-Python: >=3.11
Requires-Dist: jieba>=0.42.1
Requires-Dist: numpy>=2.3.1
Requires-Dist: ollama>=0.5.1
Requires-Dist: openai>=1.93.0
Requires-Dist: pandas>=2.3.0
Requires-Dist: rich>=14.0.0
Requires-Dist: toml>=0.10.2
Requires-Dist: tomlkit>=0.13.3
Provides-Extra: dev
Requires-Dist: pytest-cov>=4.1.0; extra == 'dev'
Requires-Dist: pytest-mock>=3.11.1; extra == 'dev'
Requires-Dist: pytest>=7.4.0; extra == 'dev'
